{
"iterations":[
{
"time":"Tue Aug 09 03:30:07 CEST 2022",
"initial_solution":{"patient_cost":"2299950", "equity_cost":"2397347"},"randomized_solution":{"patient_cost":"2185680", "equity_cost":"2205799"},"final_solution":{"patient_cost":"139785", "equity_cost":"42609"},"rectangle_archive":[{"area":"1.66113178E9","x_1":"139785","x_2":"279570","y_1":"0","y_2":"42609"}],
"solution_archive":[{"patient_cost":"146150","equity_cost":"39882"},{"patient_cost":"145985","equity_cost":"40003"},{"patient_cost":"145545","equity_cost":"40299"},{"patient_cost":"145445","equity_cost":"40401"},{"patient_cost":"145220","equity_cost":"40453"},{"patient_cost":"145085","equity_cost":"40729"},{"patient_cost":"144715","equity_cost":"40746"},{"patient_cost":"143745","equity_cost":"40760"},{"patient_cost":"143670","equity_cost":"40919"},{"patient_cost":"143095","equity_cost":"40928"},{"patient_cost":"142910","equity_cost":"41426"},{"patient_cost":"142255","equity_cost":"41525"},{"patient_cost":"142220","equity_cost":"41662"},{"patient_cost":"142200","equity_cost":"41796"},{"patient_cost":"141765","equity_cost":"42000"},{"patient_cost":"141750","equity_cost":"42054"},{"patient_cost":"141710","equity_cost":"42131"},{"patient_cost":"141700","equity_cost":"42181"},{"patient_cost":"141625","equity_cost":"42252"},{"patient_cost":"141590","equity_cost":"42281"},{"patient_cost":"141555","equity_cost":"42300"},{"patient_cost":"141540","equity_cost":"42336"},{"patient_cost":"141390","equity_cost":"42357"},{"patient_cost":"140920","equity_cost":"42472"},{"patient_cost":"139785","equity_cost":"42498"},{"patient_cost":"139785","equity_cost":"42609"}]
},{
"time":"Tue Aug 09 03:31:50 CEST 2022",
"c":"21305",
"initial_solution":{"patient_cost":"146150", "equity_cost":"39882"},"randomized_solution":{"patient_cost":"1230410", "equity_cost":"1042672"},"final_solution":{"patient_cost":"1038475", "equity_cost":"852530"},"rectangle_archive":[{"area":"-1.31698765E9","x_1":"139785","x_2":"279570","y_1":"21305","y_2":"42609"}],
"solution_archive":[{"patient_cost":"146150","equity_cost":"39882"},{"patient_cost":"145985","equity_cost":"40003"},{"patient_cost":"145545","equity_cost":"40299"},{"patient_cost":"145445","equity_cost":"40401"},{"patient_cost":"145220","equity_cost":"40453"},{"patient_cost":"145085","equity_cost":"40729"},{"patient_cost":"144715","equity_cost":"40746"},{"patient_cost":"143745","equity_cost":"40760"},{"patient_cost":"143670","equity_cost":"40919"},{"patient_cost":"143095","equity_cost":"40928"},{"patient_cost":"142910","equity_cost":"41426"},{"patient_cost":"142255","equity_cost":"41525"},{"patient_cost":"142220","equity_cost":"41662"},{"patient_cost":"142200","equity_cost":"41796"},{"patient_cost":"141765","equity_cost":"42000"},{"patient_cost":"141750","equity_cost":"42054"},{"patient_cost":"141710","equity_cost":"42131"},{"patient_cost":"141700","equity_cost":"42181"},{"patient_cost":"141625","equity_cost":"42252"},{"patient_cost":"141590","equity_cost":"42281"},{"patient_cost":"141555","equity_cost":"42300"},{"patient_cost":"141540","equity_cost":"42336"},{"patient_cost":"141390","equity_cost":"42357"},{"patient_cost":"140920","equity_cost":"42472"},{"patient_cost":"139785","equity_cost":"42498"},{"patient_cost":"139785","equity_cost":"42609"}]
},{
"time":"Tue Aug 09 03:31:50 CEST 2022",
"c":"31957",
"initial_solution":{"patient_cost":"146150", "equity_cost":"39882"},"randomized_solution":{"patient_cost":"1287460", "equity_cost":"1118779"},"final_solution":{"patient_cost":"1061780", "equity_cost":"891223"},"rectangle_archive":[{"area":"1.48898982E9","x_1":"139785","x_2":"279570","y_1":"31957","y_2":"42609"}],
"solution_archive":[{"patient_cost":"146150","equity_cost":"39882"},{"patient_cost":"145985","equity_cost":"40003"},{"patient_cost":"145545","equity_cost":"40299"},{"patient_cost":"145445","equity_cost":"40401"},{"patient_cost":"145220","equity_cost":"40453"},{"patient_cost":"145085","equity_cost":"40729"},{"patient_cost":"144715","equity_cost":"40746"},{"patient_cost":"143745","equity_cost":"40760"},{"patient_cost":"143670","equity_cost":"40919"},{"patient_cost":"143095","equity_cost":"40928"},{"patient_cost":"142910","equity_cost":"41426"},{"patient_cost":"142255","equity_cost":"41525"},{"patient_cost":"142220","equity_cost":"41662"},{"patient_cost":"142200","equity_cost":"41796"},{"patient_cost":"141765","equity_cost":"42000"},{"patient_cost":"141750","equity_cost":"42054"},{"patient_cost":"141710","equity_cost":"42131"},{"patient_cost":"141700","equity_cost":"42181"},{"patient_cost":"141625","equity_cost":"42252"},{"patient_cost":"141590","equity_cost":"42281"},{"patient_cost":"141555","equity_cost":"42300"},{"patient_cost":"141540","equity_cost":"42336"},{"patient_cost":"141390","equity_cost":"42357"},{"patient_cost":"140920","equity_cost":"42472"},{"patient_cost":"139785","equity_cost":"42498"},{"patient_cost":"139785","equity_cost":"42609"}]
},{
"time":"Tue Aug 09 03:31:50 CEST 2022",
"c":"37283",
"initial_solution":{"patient_cost":"146150", "equity_cost":"39882"},"randomized_solution":{"patient_cost":"1146060", "equity_cost":"955665"},"final_solution":{"patient_cost":"975955", "equity_cost":"786248"},"rectangle_archive":[{"area":"7.4449491E8","x_1":"139785","x_2":"279570","y_1":"37283","y_2":"42609"}],
"solution_archive":[{"patient_cost":"146150","equity_cost":"39882"},{"patient_cost":"145985","equity_cost":"40003"},{"patient_cost":"145545","equity_cost":"40299"},{"patient_cost":"145445","equity_cost":"40401"},{"patient_cost":"145220","equity_cost":"40453"},{"patient_cost":"145085","equity_cost":"40729"},{"patient_cost":"144715","equity_cost":"40746"},{"patient_cost":"143745","equity_cost":"40760"},{"patient_cost":"143670","equity_cost":"40919"},{"patient_cost":"143095","equity_cost":"40928"},{"patient_cost":"142910","equity_cost":"41426"},{"patient_cost":"142255","equity_cost":"41525"},{"patient_cost":"142220","equity_cost":"41662"},{"patient_cost":"142200","equity_cost":"41796"},{"patient_cost":"141765","equity_cost":"42000"},{"patient_cost":"141750","equity_cost":"42054"},{"patient_cost":"141710","equity_cost":"42131"},{"patient_cost":"141700","equity_cost":"42181"},{"patient_cost":"141625","equity_cost":"42252"},{"patient_cost":"141590","equity_cost":"42281"},{"patient_cost":"141555","equity_cost":"42300"},{"patient_cost":"141540","equity_cost":"42336"},{"patient_cost":"141390","equity_cost":"42357"},{"patient_cost":"140920","equity_cost":"42472"},{"patient_cost":"139785","equity_cost":"42498"},{"patient_cost":"139785","equity_cost":"42609"}]
},{
"time":"Tue Aug 09 03:31:50 CEST 2022",
"c":"39946",
"initial_solution":{"patient_cost":"145985", "equity_cost":"40003"},"randomized_solution":{"patient_cost":"1219335", "equity_cost":"1036975"},"final_solution":{"patient_cost":"1025830", "equity_cost":"843995"},"rectangle_archive":[{"area":"3.72247456E8","x_1":"139785","x_2":"279570","y_1":"39946","y_2":"42609"}],
"solution_archive":[{"patient_cost":"146150","equity_cost":"39882"},{"patient_cost":"145985","equity_cost":"40003"},{"patient_cost":"145545","equity_cost":"40299"},{"patient_cost":"145445","equity_cost":"40401"},{"patient_cost":"145220","equity_cost":"40453"},{"patient_cost":"145085","equity_cost":"40729"},{"patient_cost":"144715","equity_cost":"40746"},{"patient_cost":"143745","equity_cost":"40760"},{"patient_cost":"143670","equity_cost":"40919"},{"patient_cost":"143095","equity_cost":"40928"},{"patient_cost":"142910","equity_cost":"41426"},{"patient_cost":"142255","equity_cost":"41525"},{"patient_cost":"142220","equity_cost":"41662"},{"patient_cost":"142200","equity_cost":"41796"},{"patient_cost":"141765","equity_cost":"42000"},{"patient_cost":"141750","equity_cost":"42054"},{"patient_cost":"141710","equity_cost":"42131"},{"patient_cost":"141700","equity_cost":"42181"},{"patient_cost":"141625","equity_cost":"42252"},{"patient_cost":"141590","equity_cost":"42281"},{"patient_cost":"141555","equity_cost":"42300"},{"patient_cost":"141540","equity_cost":"42336"},{"patient_cost":"141390","equity_cost":"42357"},{"patient_cost":"140920","equity_cost":"42472"},{"patient_cost":"139785","equity_cost":"42498"},{"patient_cost":"139785","equity_cost":"42609"}]
},{
"time":"Tue Aug 09 03:31:50 CEST 2022",
"c":"41278",
"initial_solution":{"patient_cost":"142910", "equity_cost":"41426"},"randomized_solution":{"patient_cost":"1160945", "equity_cost":"970503"},"final_solution":{"patient_cost":"992925", "equity_cost":"802862"},"rectangle_archive":[{"area":"1.8605384E8","x_1":"139785","x_2":"279570","y_1":"41278","y_2":"42609"}],
"solution_archive":[{"patient_cost":"146150","equity_cost":"39882"},{"patient_cost":"145985","equity_cost":"40003"},{"patient_cost":"145545","equity_cost":"40299"},{"patient_cost":"145445","equity_cost":"40401"},{"patient_cost":"145220","equity_cost":"40453"},{"patient_cost":"145085","equity_cost":"40729"},{"patient_cost":"144715","equity_cost":"40746"},{"patient_cost":"143745","equity_cost":"40760"},{"patient_cost":"143670","equity_cost":"40919"},{"patient_cost":"143095","equity_cost":"40928"},{"patient_cost":"142910","equity_cost":"41426"},{"patient_cost":"142255","equity_cost":"41525"},{"patient_cost":"142220","equity_cost":"41662"},{"patient_cost":"142200","equity_cost":"41796"},{"patient_cost":"141765","equity_cost":"42000"},{"patient_cost":"141750","equity_cost":"42054"},{"patient_cost":"141710","equity_cost":"42131"},{"patient_cost":"141700","equity_cost":"42181"},{"patient_cost":"141625","equity_cost":"42252"},{"patient_cost":"141590","equity_cost":"42281"},{"patient_cost":"141555","equity_cost":"42300"},{"patient_cost":"141540","equity_cost":"42336"},{"patient_cost":"141390","equity_cost":"42357"},{"patient_cost":"140920","equity_cost":"42472"},{"patient_cost":"139785","equity_cost":"42498"},{"patient_cost":"139785","equity_cost":"42609"}]
},{
"time":"Tue Aug 09 03:31:50 CEST 2022",
"c":"41944",
"initial_solution":{"patient_cost":"141765", "equity_cost":"42000"},"randomized_solution":{"patient_cost":"1225250", "equity_cost":"1042861"},"final_solution":{"patient_cost":"1066730", "equity_cost":"882787"},"rectangle_archive":[{"area":"9.2957024E7","x_1":"139785","x_2":"279570","y_1":"41944","y_2":"42609"}],
"solution_archive":[{"patient_cost":"146150","equity_cost":"39882"},{"patient_cost":"145985","equity_cost":"40003"},{"patient_cost":"145545","equity_cost":"40299"},{"patient_cost":"145445","equity_cost":"40401"},{"patient_cost":"145220","equity_cost":"40453"},{"patient_cost":"145085","equity_cost":"40729"},{"patient_cost":"144715","equity_cost":"40746"},{"patient_cost":"143745","equity_cost":"40760"},{"patient_cost":"143670","equity_cost":"40919"},{"patient_cost":"143095","equity_cost":"40928"},{"patient_cost":"142910","equity_cost":"41426"},{"patient_cost":"142255","equity_cost":"41525"},{"patient_cost":"142220","equity_cost":"41662"},{"patient_cost":"142200","equity_cost":"41796"},{"patient_cost":"141765","equity_cost":"42000"},{"patient_cost":"141750","equity_cost":"42054"},{"patient_cost":"141710","equity_cost":"42131"},{"patient_cost":"141700","equity_cost":"42181"},{"patient_cost":"141625","equity_cost":"42252"},{"patient_cost":"141590","equity_cost":"42281"},{"patient_cost":"141555","equity_cost":"42300"},{"patient_cost":"141540","equity_cost":"42336"},{"patient_cost":"141390","equity_cost":"42357"},{"patient_cost":"140920","equity_cost":"42472"},{"patient_cost":"139785","equity_cost":"42498"},{"patient_cost":"139785","equity_cost":"42609"}]
},{
"time":"Tue Aug 09 03:31:50 CEST 2022",
"c":"42277",
"initial_solution":{"patient_cost":"141590", "equity_cost":"42281"},"randomized_solution":{"patient_cost":"1220075", "equity_cost":"1039390"},"final_solution":{"patient_cost":"1006420", "equity_cost":"823012"},"rectangle_archive":[{"area":"4.640862E7","x_1":"139785","x_2":"279570","y_1":"42277","y_2":"42609"}],
"solution_archive":[{"patient_cost":"146150","equity_cost":"39882"},{"patient_cost":"145985","equity_cost":"40003"},{"patient_cost":"145545","equity_cost":"40299"},{"patient_cost":"145445","equity_cost":"40401"},{"patient_cost":"145220","equity_cost":"40453"},{"patient_cost":"145085","equity_cost":"40729"},{"patient_cost":"144715","equity_cost":"40746"},{"patient_cost":"143745","equity_cost":"40760"},{"patient_cost":"143670","equity_cost":"40919"},{"patient_cost":"143095","equity_cost":"40928"},{"patient_cost":"142910","equity_cost":"41426"},{"patient_cost":"142255","equity_cost":"41525"},{"patient_cost":"142220","equity_cost":"41662"},{"patient_cost":"142200","equity_cost":"41796"},{"patient_cost":"141765","equity_cost":"42000"},{"patient_cost":"141750","equity_cost":"42054"},{"patient_cost":"141710","equity_cost":"42131"},{"patient_cost":"141700","equity_cost":"42181"},{"patient_cost":"141625","equity_cost":"42252"},{"patient_cost":"141590","equity_cost":"42281"},{"patient_cost":"141555","equity_cost":"42300"},{"patient_cost":"141540","equity_cost":"42336"},{"patient_cost":"141390","equity_cost":"42357"},{"patient_cost":"140920","equity_cost":"42472"},{"patient_cost":"139785","equity_cost":"42498"},{"patient_cost":"139785","equity_cost":"42609"}]
},{
"time":"Tue Aug 09 03:31:50 CEST 2022",
"c":"42443",
"initial_solution":{"patient_cost":"140920", "equity_cost":"42472"},"randomized_solution":{"patient_cost":"1227845", "equity_cost":"1045363"},"final_solution":{"patient_cost":"1012620", "equity_cost":"829486"},"rectangle_archive":[{"area":"2.320431E7","x_1":"139785","x_2":"279570","y_1":"42443","y_2":"42609"}],
"solution_archive":[{"patient_cost":"146150","equity_cost":"39882"},{"patient_cost":"145985","equity_cost":"40003"},{"patient_cost":"145545","equity_cost":"40299"},{"patient_cost":"145445","equity_cost":"40401"},{"patient_cost":"145220","equity_cost":"40453"},{"patient_cost":"145085","equity_cost":"40729"},{"patient_cost":"144715","equity_cost":"40746"},{"patient_cost":"143745","equity_cost":"40760"},{"patient_cost":"143670","equity_cost":"40919"},{"patient_cost":"143095","equity_cost":"40928"},{"patient_cost":"142910","equity_cost":"41426"},{"patient_cost":"142255","equity_cost":"41525"},{"patient_cost":"142220","equity_cost":"41662"},{"patient_cost":"142200","equity_cost":"41796"},{"patient_cost":"141765","equity_cost":"42000"},{"patient_cost":"141750","equity_cost":"42054"},{"patient_cost":"141710","equity_cost":"42131"},{"patient_cost":"141700","equity_cost":"42181"},{"patient_cost":"141625","equity_cost":"42252"},{"patient_cost":"141590","equity_cost":"42281"},{"patient_cost":"141555","equity_cost":"42300"},{"patient_cost":"141540","equity_cost":"42336"},{"patient_cost":"141390","equity_cost":"42357"},{"patient_cost":"140920","equity_cost":"42472"},{"patient_cost":"139785","equity_cost":"42498"},{"patient_cost":"139785","equity_cost":"42609"}]
},{
"time":"Tue Aug 09 03:31:50 CEST 2022",
"c":"42526",
"initial_solution":{"patient_cost":"139785", "equity_cost":"42498"},"randomized_solution":{"patient_cost":"1232470", "equity_cost":"1057442"},"final_solution":{"patient_cost":"1042575", "equity_cost":"865712"},"rectangle_archive":[{"area":"1.1602155E7","x_1":"139785","x_2":"279570","y_1":"42526","y_2":"42609"}],
"solution_archive":[{"patient_cost":"146150","equity_cost":"39882"},{"patient_cost":"145985","equity_cost":"40003"},{"patient_cost":"145545","equity_cost":"40299"},{"patient_cost":"145445","equity_cost":"40401"},{"patient_cost":"145220","equity_cost":"40453"},{"patient_cost":"145085","equity_cost":"40729"},{"patient_cost":"144715","equity_cost":"40746"},{"patient_cost":"143745","equity_cost":"40760"},{"patient_cost":"143670","equity_cost":"40919"},{"patient_cost":"143095","equity_cost":"40928"},{"patient_cost":"142910","equity_cost":"41426"},{"patient_cost":"142255","equity_cost":"41525"},{"patient_cost":"142220","equity_cost":"41662"},{"patient_cost":"142200","equity_cost":"41796"},{"patient_cost":"141765","equity_cost":"42000"},{"patient_cost":"141750","equity_cost":"42054"},{"patient_cost":"141710","equity_cost":"42131"},{"patient_cost":"141700","equity_cost":"42181"},{"patient_cost":"141625","equity_cost":"42252"},{"patient_cost":"141590","equity_cost":"42281"},{"patient_cost":"141555","equity_cost":"42300"},{"patient_cost":"141540","equity_cost":"42336"},{"patient_cost":"141390","equity_cost":"42357"},{"patient_cost":"140920","equity_cost":"42472"},{"patient_cost":"139785","equity_cost":"42498"},{"patient_cost":"139785","equity_co