{
  "iterations": [
    {
      "time": "Tue Aug 09 03:29:47 CEST 2022",
      "initial_solution": {
        "patient_cost": "1167590",
        "equity_cost": "1222362"
      },
      "randomized_solution": {
        "patient_cost": "1061050",
        "equity_cost": "1057884"
      },
      "final_solution": {
        "patient_cost": "58965",
        "equity_cost": "7723"
      },
      "rectangle_archive": [
        {
          "area": "4.55386688E8",
          "x_1": "58965",
          "x_2": "117930",
          "y_1": "0",
          "y_2": "7723"
        }
      ],
      "solution_archive": [
        {
          "patient_cost": "71990",
          "equity_cost": "6526"
        },
        {
          "patient_cost": "66750",
          "equity_cost": "6715"
        },
        {
          "patient_cost": "66525",
          "equity_cost": "6758"
        },
        {
          "patient_cost": "66500",
          "equity_cost": "6893"
        },
        {
          "patient_cost": "65435",
          "equity_cost": "7161"
        },
        {
          "patient_cost": "60420",
          "equity_cost": "7164"
        },
        {
          "patient_cost": "60080",
          "equity_cost": "7253"
        },
        {
          "patient_cost": "59265",
          "equity_cost": "7278"
        },
        {
          "patient_cost": "59255",
          "equity_cost": "7286"
        },
        {
          "patient_cost": "59250",
          "equity_cost": "7316"
        },
        {
          "patient_cost": "59245",
          "equity_cost": "7438"
        },
        {
          "patient_cost": "59195",
          "equity_cost": "7498"
        },
        {
          "patient_cost": "59190",
          "equity_cost": "7532"
        },
        {
          "patient_cost": "59135",
          "equity_cost": "7552"
        },
        {
          "patient_cost": "59130",
          "equity_cost": "7568"
        },
        {
          "patient_cost": "59125",
          "equity_cost": "7570"
        },
        {
          "patient_cost": "59065",
          "equity_cost": "7586"
        },
        {
          "patient_cost": "58995",
          "equity_cost": "7604"
        },
        {
          "patient_cost": "58990",
          "equity_cost": "7638"
        },
        {
          "patient_cost": "58975",
          "equity_cost": "7666"
        },
        {
          "patient_cost": "58965",
          "equity_cost": "7723"
        },
        {
          "patient_cost": "58965",
          "equity_cost": "7723"
        }
      ]
    },
    {
      "time": "Tue Aug 09 03:30:29 CEST 2022",
      "c": "3862",
      "initial_solution": {
        "patient_cost": "71990",
        "equity_cost": "6526"
      },
      "randomized_solution": {
        "patient_cost": "596060",
        "equity_cost": "495494"
      },
      "final_solution": {
        "patient_cost": "457930",
        "equity_cost": "356931"
      },
      "rectangle_archive": [
        {
          "area": "2.27663872E8",
          "x_1": "58965",
          "x_2": "117930",
          "y_1": "3862",
          "y_2": "7723"
        }
      ],
      "solution_archive": [
        {
          "patient_cost": "71990",
          "equity_cost": "6526"
        },
        {
          "patient_cost": "66750",
          "equity_cost": "6715"
        },
        {
          "patient_cost": "66525",
          "equity_cost": "6758"
        },
        {
          "patient_cost": "66500",
          "equity_cost": "6893"
        },
        {
          "patient_cost": "65435",
          "equity_cost": "7161"
        },
        {
          "patient_cost": "60420",
          "equity_cost": "7164"
        },
        {
          "patient_cost": "60080",
          "equity_cost": "7253"
        },
        {
          "patient_cost": "59265",
          "equity_cost": "7278"
        },
        {
          "patient_cost": "59255",
          "equity_cost": "7286"
        },
        {
          "patient_cost": "59250",
          "equity_cost": "7316"
        },
        {
          "patient_cost": "59245",
          "equity_cost": "7438"
        },
        {
          "patient_cost": "59195",
          "equity_cost": "7498"
        },
        {
          "patient_cost": "59190",
          "equity_cost": "7532"
        },
        {
          "patient_cost": "59135",
          "equity_cost": "7552"
        },
        {
          "patient_cost": "59130",
          "equity_cost": "7568"
        },
        {
          "patient_cost": "59125",
          "equity_cost": "7570"
        },
        {
          "patient_cost": "59065",
          "equity_cost": "7586"
        },
        {
          "patient_cost": "58995",
          "equity_cost": "7604"
        },
        {
          "patient_cost": "58990",
          "equity_cost": "7638"
        },
        {
          "patient_cost": "58975",
          "equity_cost": "7666"
        },
        {
          "patient_cost": "58965",
          "equity_cost": "7723"
        },
        {
          "patient_cost": "58965",
          "equity_cost": "7723"
        }
      ]
    },
    {
      "time": "Tue Aug 09 03:30:29 CEST 2022",
      "c": "5793",
      "initial_solution": {
        "patient_cost": "71990",
        "equity_cost": "6526"
      },
      "randomized_solution": {
        "patient_cost": "575010",
        "equity_cost": "475425"
      },
      "final_solution": {
        "patient_cost": "434840",
        "equity_cost": "333155"
      },
      "rectangle_archive": [
        {
          "area": "1.13802448E8",
          "x_1": "58965",
          "x_2": "117930",
          "y_1": "5793",
          "y_2": "7723"
        }
      ],
      "solution_archive": [
        {
          "patient_cost": "71990",
          "equity_cost": "6526"
        },
        {
          "patient_cost": "66750",
          "equity_cost": "6715"
        },
        {
          "patient_cost": "66525",
          "equity_cost": "6758"
        },
        {
          "patient_cost": "66500",
          "equity_cost": "6893"
        },
        {
          "patient_cost": "65435",
          "equity_cost": "7161"
        },
        {
          "patient_cost": "60420",
          "equity_cost": "7164"
        },
        {
          "patient_cost": "60080",
          "equity_cost": "7253"
        },
        {
          "patient_cost": "59265",
          "equity_cost": "7278"
        },
        {
          "patient_cost": "59255",
          "equity_cost": "7286"
        },
        {
          "patient_cost": "59250",
          "equity_cost": "7316"
        },
        {
          "patient_cost": "59245",
          "equity_cost": "7438"
        },
        {
          "patient_cost": "59195",
          "equity_cost": "7498"
        },
        {
          "patient_cost": "59190",
          "equity_cost": "7532"
        },
        {
          "patient_cost": "59135",
          "equity_cost": "7552"
        },
        {
          "patient_cost": "59130",
          "equity_cost": "7568"
        },
        {
          "patient_cost": "59125",
          "equity_cost": "7570"
        },
        {
          "patient_cost": "59065",
          "equity_cost": "7586"
        },
        {
          "patient_cost": "58995",
          "equity_cost": "7604"
        },
        {
          "patient_cost": "58990",
          "equity_cost": "7638"
        },
        {
          "patient_cost": "58975",
          "equity_cost": "7666"
        },
        {
          "patient_cost": "58965",
          "equity_cost": "7723"
        },
        {
          "patient_cost": "58965",
          "equity_cost": "7723"
        }
      ]
    },
    {
      "time": "Tue Aug 09 03:30:29 CEST 2022",
      "c": "6758",
      "initial_solution": {
        "patient_cost": "66525",
        "equity_cost": "6758"
      },
      "randomized_solution": {
        "patient_cost": "591450",
        "equity_cost": "494435"
      },
      "final_solution": {
        "patient_cost": "454545",
        "equity_cost": "358066"
      },
      "rectangle_archive": [
        {
          "area": "5.6901224E7",
          "x_1": "58965",
          "x_2": "117930",
          "y_1": "6758",
          "y_2": "7723"
        }
      ],
      "solution_archive": [
        {
          "patient_cost": "71990",
          "equity_cost": "6526"
        },
        {
          "patient_cost": "66750",
          "equity_cost": "6715"
        },
        {
          "patient_cost": "66525",
          "equity_cost": "6758"
        },
        {
          "patient_cost": "66500",
          "equity_cost": "6893"
        },
        {
          "patient_cost": "65435",
          "equity_cost": "7161"
        },
        {
          "patient_cost": "60420",
          "equity_cost": "7164"
        },
        {
          "patient_cost": "60080",
          "equity_cost": "7253"
        },
        {
          "patient_cost": "59265",
          "equity_cost": "7278"
        },
        {
          "patient_cost": "59255",
          "equity_cost": "7286"
        },
        {
          "patient_cost": "59250",
          "equity_cost": "7316"
        },
        {
          "patient_cost": "59245",
          "equity_cost": "7438"
        },
        {
          "patient_cost": "59195",
          "equity_cost": "7498"
        },
        {
          "patient_cost": "59190",
          "equity_cost": "7532"
        },
        {
          "patient_cost": "59135",
          "equity_cost": "7552"
        },
        {
          "patient_cost": "59130",
          "equity_cost": "7568"
        },
        {
          "patient_cost": "59125",
          "equity_cost": "7570"
        },
        {
          "patient_cost": "59065",
          "equity_cost": "7586"
        },
        {
          "patient_cost": "58995",
          "equity_cost": "7604"
        },
        {
          "patient_cost": "58990",
          "equity_cost": "7638"
        },
        {
          "patient_cost": "58975",
          "equity_cost": "7666"
        },
        {
          "patient_cost": "58965",
          "equity_cost": "7723"
        },
        {
          "patient_cost": "58965",
          "equity_cost": "7723"
        }
      ]
    },
    {
      "time": "Tue Aug 09 03:30:29 CEST 2022",
      "c": "7241",
      "initial_solution": {
        "patient_cost": "60080",
        "equity_cost": "7253"
      },
      "randomized_solution": {
        "patient_cost": "610455",
        "equity_cost": "515476"
      },
      "final_solution": {
        "patient_cost": "492850",
        "equity_cost": "399261"
      },
      "rectangle_archive": [
        {
          "area": "2.842113E7",
          "x_1": "58965",
          "x_2": "117930",
          "y_1": "7241",
          "y_2": "7723"
        }
      ],
      "solution_archive": [
        {
          "patient_cost": "71990",
          "equity_cost": "6526"
        },
        {
          "patient_cost": "66750",
          "equity_cost": "6715"
        },
        {
          "patient_cost": "66525",
          "equity_cost": "6758"
        },
        {
          "patient_cost": "66500",
          "equity_cost": "6893"
        },
        {
          "patient_cost": "65435",
          "equity_cost": "7161"
        },
        {
          "patient_cost": "60420",
          "equity_cost": "7164"
        },
        {
          "patient_cost": "60080",
          "equity_cost": "7253"
        },
        {
          "patient_cost": "59265",
          "equity_cost": "7278"
        },
        {
          "patient_cost": "59255",
          "equity_cost": "7286"
        },
        {
          "patient_cost": "59250",
          "equity_cost": "7316"
        },
        {
          "patient_cost": "59245",
          "equity_cost": "7438"
        },
        {
          "patient_cost": "59195",
          "equity_cost": "7498"
        },
        {
          "patient_cost": "59190",
          "equity_cost": "7532"
        },
        {
          "patient_cost": "59135",
          "equity_cost": "7552"
        },
        {
          "patient_cost": "59130",
          "equity_cost": "7568"
        },
        {
          "patient_cost": "59125",
          "equity_cost": "7570"
        },
        {
          "patient_cost": "59065",
          "equity_cost": "7586"
        },
        {
          "patient_cost": "58995",
          "equity_cost": "7604"
        },
        {
          "patient_cost": "58990",
          "equity_cost": "7638"
        },
        {
          "patient_cost": "58975",
          "equity_cost": "7666"
        },
        {
          "patient_cost": "58965",
          "equity_cost": "7723"
        },
        {
          "patient_cost": "58965",
          "equity_cost": "7723"
        }
      ]
    },
    {
      "time": "Tue Aug 09 03:30:29 CEST 2022",
      "c": "7482",
      "initial_solution": {
        "patient_cost": "59195",
        "equity_cost": "7498"
      },
      "randomized_solution": {
        "patient_cost": "629180",
        "equity_cost": "538475"
      },
      "final_solution": {
        "patient_cost": "496360",
        "equity_cost": "405046"
      },
      "rectangle_archive": [
        {
          "area": "1.4210565E7",
          "x_1": "58965",
          "x_2": "117930",
          "y_1": "7482",
          "y_2": "7723"
        }
      ],
      "solution_archive": [
        {
          "patient_cost": "71990",
          "equity_cost": "6526"
        },
        {
          "patient_cost": "66750",
          "equity_cost": "6715"
        },
        {
          "patient_cost": "66525",
          "equity_cost": "6758"
        },
        {
          "patient_cost": "66500",
          "equity_cost": "6893"
        },
        {
          "patient_cost": "65435",
          "equity_cost": "7161"
        },
        {
          "patient_cost": "60420",
          "equity_cost": "7164"
        },
        {
          "patient_cost": "60080",
          "equity_cost": "7253"
        },
        {
          "patient_cost": "59265",
          "equity_cost": "7278"
        },
        {
          "patient_cost": "59255",
          "equity_cost": "7286"
        },
        {
          "patient_cost": "59250",
          "equity_cost": "7316"
        },
        {
          "patient_cost": "59245",
          "equity_cost": "7438"
        },
        {
          "patient_cost": "59195",
          "equity_cost": "7498"
        },
        {
          "patient_cost": "59190",
          "equity_cost": "7532"
        },
        {
          "patient_cost": "59135",
          "equity_cost": "7552"
        },
        {
          "patient_cost": "59130",
          "equity_cost": "7568"
        },
        {
          "patient_cost": "59125",
          "equity_cost": "7570"
        },
        {
          "patient_cost": "59065",
          "equity_cost": "7586"
        },
        {
          "patient_cost": "58995",
          "equity_cost": "7604"
        }
      ]
    }
  ]
}
